[
  {
    "trade_id": null,
    "price": 119291.5,
    "amount": 6,
    "direction": "sell",
    "timestamp": 1755010582361
  },
  {
    "trade_id": null,
    "price": 119291.5,
    "amount": 36,
    "direction": "sell",
    "timestamp": 1755010587879
  },
  {
    "trade_id": null,
    "price": 119291.5,
    "amount": 30,
    "direction": "sell",
    "timestamp": 1755010590473
  },
  {
    "trade_id": null,
    "price": 119291.6,
    "amount": 82,
    "direction": "buy",
    "timestamp": 1755010596843
  },
  {
    "trade_id": null,
    "price": 119291.5,
    "amount": 2,
    "direction": "sell",
    "timestamp": 1755010599044
  },
  {
    "trade_id": null,
    "price": 119291.6,
    "amount": 110,
    "direction": "buy",
    "timestamp": 1755010600123
  },
  {
    "trade_id": null,
    "price": 119291.6,
    "amount": 8,
    "direction": "buy",
    "timestamp": 1755010603783
  },
  {
    "trade_id": null,
    "price": 119291.6,
    "amount": 2,
    "direction": "buy",
    "timestamp": 1755010606352
  },
  {
    "trade_id": null,
    "price": 119291.6,
    "amount": 66,
    "direction": "buy",
    "timestamp": 1755010606352
  },
  {
    "trade_id": null,
    "price": 119291.8,
    "amount": 10,
    "direction": "buy",
    "timestamp": 1755010606850
  },
  {
    "trade_id": null,
    "price": 119305.0,
    "amount": 2,
    "direction": "buy",
    "timestamp": 1755010607120
  },
  {
    "trade_id": null,
    "price": 119307.1,
    "amount": 6,
    "direction": "buy",
    "timestamp": 1755010610707
  },
  {
    "trade_id": null,
    "price": 119307.1,
    "amount": 52,
    "direction": "buy",
    "timestamp": 1755010611243
  },
  {
    "trade_id": null,
    "price": 119307.1,
    "amount": 58,
    "direction": "buy",
    "timestamp": 1755010611243
  }
]